lcapygui/__init__.py
lcapygui/annotation.py
lcapygui/annotations.py
lcapygui/sketch_library.py
lcapygui/components/__init__.py
lcapygui/components/admittance.py
lcapygui/components/annotation.py
lcapygui/components/bipole.py
lcapygui/components/bjt.py
lcapygui/components/capacitor.py
lcapygui/components/cccs.py
lcapygui/components/ccvs.py
lcapygui/components/component.py
lcapygui/components/connection.py
lcapygui/components/controlledcomponent.py
lcapygui/components/cpe.py
lcapygui/components/cpt_maker.py
lcapygui/components/current_source.py
lcapygui/components/diode.py
lcapygui/components/fdopamp.py
lcapygui/components/ferritebead.py
lcapygui/components/fixed.py
lcapygui/components/impedance.py
lcapygui/components/inamp.py
lcapygui/components/inductor.py
lcapygui/components/jfet.py
lcapygui/components/mosfet.py
lcapygui/components/opamp.py
lcapygui/components/opencircuit.py
lcapygui/components/picture.py
lcapygui/components/port.py
lcapygui/components/pos.py
lcapygui/components/resistor.py
lcapygui/components/sketch.py
lcapygui/components/stretchy.py
lcapygui/components/svgparse.py
lcapygui/components/switch.py
lcapygui/components/tf.py
lcapygui/components/transformer.py
lcapygui/components/transistor.py
lcapygui/components/utils.py
lcapygui/components/vccs.py
lcapygui/components/vcvs.py
lcapygui/components/voltage_source.py
lcapygui/components/wire.py
lcapygui/data/icon/lcapy-gui-small.png
lcapygui/data/icon/lcapy-gui-small.svg
lcapygui/data/icon/lcapy-gui.ico
lcapygui/data/icon/lcapy-gui.png
lcapygui/data/icon/lcapy-gui.svg
lcapygui/data/icon/lcapy-gui_wide.svg
lcapygui/data/lib/AC/AC-voltage-divider1.sch
lcapygui/data/lib/DC/DC-voltage-divider1.sch
lcapygui/data/lib/IVP/Vstep-RLC2-IVP.sch
lcapygui/data/lib/components/basic.sch
lcapygui/data/lib/components/capacitors.sch
lcapygui/data/lib/components/diodes.sch
lcapygui/data/lib/components/inductors.sch
lcapygui/data/lib/components/resistors.sch
lcapygui/data/lib/components/transistors.sch
lcapygui-0.94.dist-info/LICENSE.md
lcapygui-0.94.dist-info/METADATA
lcapygui-0.94.dist-info/WHEEL
lcapygui-0.94.dist-info/entry_points.txt
lcapygui-0.94.dist-info/top_level.txt
lcapygui-0.94.dist-info/RECORD
