Metadata-Version: 2.1
Name: lcapygui
Version: 0.94
Summary: A GUI for lcapy
Home-page: https://github.com/mph-/lcapy-gui
Author: Michael Hayes, Jordan Hay
License: MIT
Project-URL: Bug Tracker, https://github.com/mph-/lcapy-gui
Platform: UNKNOWN
Classifier: Programming Language :: Python :: 3
Classifier: License :: OSI Approved :: MIT License
Classifier: Operating System :: OS Independent
Requires-Python: >=3.7
Requires-Dist: lcapy (>=1.17)
Requires-Dist: matplotlib
Requires-Dist: numpy
Requires-Dist: pillow (>=9.4.0)
Requires-Dist: pyshortcuts
Requires-Dist: setuptools
Requires-Dist: svgpath2mpl
Requires-Dist: svgpathtools
Requires-Dist: tk
Requires-Dist: tkhtmlview
Provides-Extra: doc
Requires-Dist: ipython ; extra == 'doc'
Requires-Dist: sphinx ; extra == 'doc'
Requires-Dist: sphinx-rtd-theme ; extra == 'doc'
Provides-Extra: release
Requires-Dist: pyinstaller ; extra == 'release'
